curvefit_gd/__init__.py
curvefit_gd/gradient_descent_optimizer.py
curvefit_gd-1.3.0.dist-info/LICENSE
curvefit_gd-1.3.0.dist-info/METADATA
curvefit_gd-1.3.0.dist-info/WHEEL
curvefit_gd-1.3.0.dist-info/top_level.txt
curvefit_gd-1.3.0.dist-info/RECORD
