Metadata-Version: 2.1
Name: curvefit_gd
Version: 1.3.0
Summary: A gradient descent optimizer that helps fitting multivariate nonlinear curves to data
Author-email: Behzad Aminian <aminian.bz@gmail.com>
License: MIT License
Keywords: Gradient Descent,curve fitting,nonlinear,multivariate,machine learning,optimization
Classifier: Programming Language :: Python :: 3
Classifier: License :: OSI Approved :: MIT License
Classifier: Operating System :: OS Independent
Classifier: Intended Audience :: Developers
Classifier: Intended Audience :: Science/Research
Classifier: Topic :: Scientific/Engineering :: Mathematics
Classifier: Topic :: Scientific/Engineering :: Artificial Intelligence
Requires-Python: >=3.7
License-File: LICENSE
Requires-Dist: numpy
